token_api.py
token_api-1.0.0.dist-info/WHEEL
token_api-1.0.0.dist-info/METADATA
token_api-1.0.0.dist-info/RECORD
