Metadata-Version: 2.1
Name: token-api
Version: 1.0.0
Summary: Make a Token encryption
License: GNU-V3
Author: OwoNicoo
Requires-Python: >=3.9,<4.0
Classifier: License :: Other/Proprietary License
Classifier: Programming Language :: Python :: 3
Classifier: Programming Language :: Python :: 3.10
Classifier: Programming Language :: Python :: 3.9
